LsBook/__init__.py
LsBook/lsbook.py
LsBook/assets/i18n/ar.json
LsBook/assets/i18n/bn.json
LsBook/assets/i18n/ca.json
LsBook/assets/i18n/cs.json
LsBook/assets/i18n/de.json
LsBook/assets/i18n/el.json
LsBook/assets/i18n/en.json
LsBook/assets/i18n/es.json
LsBook/assets/i18n/fa.json
LsBook/assets/i18n/fi.json
LsBook/assets/i18n/fr.json
LsBook/assets/i18n/he.json
LsBook/assets/i18n/it.json
LsBook/assets/i18n/ja.json
LsBook/assets/i18n/ko.json
LsBook/assets/i18n/nl.json
LsBook/assets/i18n/no.json
LsBook/assets/i18n/pl.json
LsBook/assets/i18n/pt.json
LsBook/assets/i18n/ro.json
LsBook/assets/i18n/ru.json
LsBook/assets/i18n/sv.json
LsBook/assets/i18n/tr.json
LsBook/assets/i18n/uk.json
LsBook/assets/i18n/vi.json
LsBook/assets/i18n/zh-cn.json
LsBook/assets/i18n/zh-hans.json
LsBook/assets/i18n/zh-tw.json
LsBook/assets/lsbook/jquery-3.3.1.min.js
LsBook/assets/lsbook/jquery.mark.js
LsBook/assets/lsbook/lsbook.js
LsBook/assets/lsbook/lsbook.min.js
LsBook/assets/lsbook/lsbook.min.js.map
LsBook/assets/lsbook/images/apple-touch-icon-precomposed-152.png
LsBook/assets/lsbook/images/favicon.ico
LsBook/assets/lsbook/jquery_mar/jquery.mark.es6.js
LsBook/assets/lsbook/jquery_mar/jquery.mark.es6.min.js
LsBook/assets/lsbook/jquery_mar/jquery.mark.js
LsBook/assets/lsbook/jquery_mar/jquery.mark.min.js
LsBook/assets/lsbook/jquery_mar/mark.es6.js
LsBook/assets/lsbook/jquery_mar/mark.es6.min.js
LsBook/assets/lsbook/jquery_mar/mark.js
LsBook/assets/lsbook/jquery_mar/mark.min.js
LsBook/assets/lsbook/katex/README.md
LsBook/assets/lsbook/katex/katex.css
LsBook/assets/lsbook/katex/katex.js
LsBook/assets/lsbook/katex/katex.min.css
LsBook/assets/lsbook/katex/katex.min.js
LsBook/assets/lsbook/katex/katex.mjs
LsBook/assets/lsbook/katex/contrib/auto-render.js
LsBook/assets/lsbook/katex/contrib/auto-render.min.js
LsBook/assets/lsbook/katex/contrib/auto-render.mjs
LsBook/assets/lsbook/katex/contrib/copy-tex.css
LsBook/assets/lsbook/katex/contrib/copy-tex.js
LsBook/assets/lsbook/katex/contrib/copy-tex.min.css
LsBook-2.0.3.dist-info/LICENSE
LsBook-2.0.3.dist-info/METADATA
LsBook-2.0.3.dist-info/WHEEL
LsBook-2.0.3.dist-info/entry_points.txt
LsBook-2.0.3.dist-info/top_level.txt
LsBook-2.0.3.dist-info/zip-safe
LsBook-2.0.3.dist-info/RECORD
