Metadata-Version: 2.1
Name: LsBook
Version: 2.0.3
Summary: markdown 静态网页生成器
Home-page: https://github.com/liushilive/lsbook
Author: 刘士
Author-email: liushilive@outlook.com
License: MIT
Project-URL: 样板, https://liushilive.github.io
Keywords: lsbook md
Platform: UNKNOWN
Classifier: Development Status :: 5 - Production/Stable
Classifier: Intended Audience :: Developers
Classifier: License :: OSI Approved :: MIT License
Classifier: Natural Language :: Chinese (Simplified)
Classifier: Programming Language :: Python
Classifier: Programming Language :: Python :: 3.7
Classifier: Programming Language :: Python :: Implementation :: CPython
Classifier: Programming Language :: Python :: Implementation :: PyPy
License-File: LICENSE
